{
  "proxyDomain": "",
  "listeningAddress": "",
  "listeningPortHTTP": 80,
  "listeningPortHTTPS": 443,
  "target": "",
  "targetResources": "",
  "forwardTo": "",
  "rules": "",
  "terminateTriggers": "",
  "terminateRedirectUrl": "",
  "unauthRedirectUrl": "",
  "trackingCookie": "",
  "trackingParam": "",
  "jsRules": "base641:base641,base642:base642",
  "jsReflectParam": "",
  "debug": false,
  "forceHTTPS": false,
  "forceHTTP": false,
  "dynamicMode": false,
  "logPostOnly": false,
  "disableSecurity": false,
  "log": "",
  "plugins": "",
  "credParams": "base641,base642;base643,base644",
  "SessionKeys": "",
  "subLink": "user,URL,entry.number",
  "cert": "",
  "certKey": "",
  "certPool": "",
  "botList": "",
  "allowSecureCookies":true
}